pigsqueeze/__init__.py
pigsqueeze/cli.py
pigsqueeze/pigsqueeze.py
pigsqueeze-2.0.1.dist-info/entry_points.txt
pigsqueeze-2.0.1.dist-info/LICENSE
pigsqueeze-2.0.1.dist-info/WHEEL
pigsqueeze-2.0.1.dist-info/METADATA
pigsqueeze-2.0.1.dist-info/RECORD
