Metadata-Version: 2.1
Name: pigsqueeze
Version: 2.0.1
Summary: A library to write and read arbitrary data to and from image files. You probably already know why you need it.
Home-page: https://github.com/timwedde/pigsqueeze
License: MIT
Author: Tim Wedde
Author-email: timwedde@icloud.com
Requires-Python: >=3.8,<4.0
Classifier: License :: OSI Approved :: MIT License
Classifier: Programming Language :: Python :: 3
Classifier: Programming Language :: Python :: 3.8
Classifier: Programming Language :: Python :: 3.9
Requires-Dist: plum-py (>=0.4.0,<0.5.0)
Project-URL: Repository, https://github.com/timwedde/pigsqueeze
